sugar/__init__.py
sugar/_modidx.py
sugar/abi.py
sugar/chains.py
sugar/config.py
sugar/deposit.py
sugar/helpers.py
sugar/pool.py
sugar/price.py
sugar/quote.py
sugar/superswap.py
sugar/swap.py
sugar/token.py
sugar/abis/interchain_account_router.json
sugar/abis/interchain_router.json
sugar/abis/nfpm.json
sugar/abis/price_oracle.json
sugar/abis/quoter.json
sugar/abis/router.json
sugar/abis/slipstream.json
sugar/abis/sugar.json
sugar/abis/sugar_rewards.json
sugar/abis/swapper.json
sugar_sdk-0.3.1.dist-info/licenses/LICENSE
sugar_sdk-0.3.1.dist-info/METADATA
sugar_sdk-0.3.1.dist-info/WHEEL
sugar_sdk-0.3.1.dist-info/entry_points.txt
sugar_sdk-0.3.1.dist-info/top_level.txt
sugar_sdk-0.3.1.dist-info/RECORD
