Metadata-Version: 2.4
Name: sugar-sdk
Version: 0.3.1
Summary: Sugar SDK
Home-page: https://github.com/velodrome-finance/sugar-sdk/
Author: Velodrome Finance
Author-email: hello@velodrome.finance
License: Apache Software License 2.0
Keywords: sugar
Classifier: Development Status :: 3 - Alpha
Classifier: Intended Audience :: Developers
Classifier: Natural Language :: English
Classifier: Programming Language :: Python :: 3.9
Classifier: Programming Language :: Python :: 3.10
Classifier: Programming Language :: Python :: 3.11
Classifier: Programming Language :: Python :: 3.12
Classifier: Programming Language :: Python :: 3.13
Classifier: License :: OSI Approved :: Apache Software License
Requires-Python: >=3.9
License-File: LICENSE
Requires-Dist: python-dotenv
Requires-Dist: pyyaml
Requires-Dist: fastcore
Requires-Dist: web3===7.12.0
Requires-Dist: networkx
Requires-Dist: requests
Requires-Dist: async-lru
Requires-Dist: cachetools
Provides-Extra: dev
Dynamic: author
Dynamic: author-email
Dynamic: classifier
Dynamic: description
Dynamic: description-content-type
Dynamic: home-page
Dynamic: keywords
Dynamic: license
Dynamic: license-file
Dynamic: provides-extra
Dynamic: requires-dist
Dynamic: requires-python
Dynamic: summary
